{
 "t": 1784311345852,
 "when": "2026-07-17T18:02:25.852Z",
 "app": "plan2vr 2026-07-13",
 "session": "2026-07-17T18:01:01.453Z",
 "plan": "plans/home-l1-biglaundry.json",
 "plan_source": {
  "kind": "dxf",
  "floor": "1"
 },
 "x": -84,
 "y": -59.3,
 "yaw": -3.23,
 "transcript": "",
 "strokes": [
  {
   "t": 1784311307710,
   "pts": [
    [
     -15.8,
     -95.5,
     0.208
    ],
    [
     1.4,
     -95.4,
     0.179
    ],
    [
     8.2,
     -95.4,
     0.139
    ],
    [
     14.6,
     -95.4,
     0.189
    ],
    [
     15.2,
     -95.4,
     0.197
    ],
    [
     15.1,
     -95.4,
     0.237
    ],
    [
     10.1,
     -95.4,
     0.221
    ],
    [
     -2.7,
     -95.4,
     0.154
    ],
    [
     -15.9,
     -95.5,
     0.08
    ],
    [
     -25.8,
     -95.1,
     0.008
    ],
    [
     -31.4,
     -95.5,
     0.027
    ],
    [
     -27.6,
     -94.8,
     0.008
    ],
    [
     -11.3,
     -95.4,
     0.122
    ],
    [
     4.4,
     -95.4,
     0.176
    ],
    [
     10.7,
     -95.4,
     0.231
    ],
    [
     8.3,
     -95.4,
     0.274
    ],
    [
     -5.7,
     -95.4,
     0.235
    ],
    [
     -20.7,
     -95.5,
     0.146
    ],
    [
     -18.9,
     -95.5,
     0.158
    ],
    [
     -6.8,
     -95.4,
     0.2
    ],
    [
     8.9,
     -95.4,
     0.226
    ],
    [
     11.3,
     -95.4,
     0.238
    ],
    [
     1.6,
     -95.4,
     0.232
    ],
    [
     -4.4,
     -95.4,
     0.147
    ]
   ]
  },
  {
   "t": 1784311309953,
   "pts": [
    [
     -53.9,
     -88.8,
     0.009
    ],
    [
     -49,
     -82.2,
     0.01
    ],
    [
     -42,
     -80.6,
     0.01
    ],
    [
     -47.1,
     -85,
     0.01
    ],
    [
     -49.7,
     -95.5,
     0.059
    ],
    [
     -43,
     -95.5,
     0.156
    ],
    [
     -40.6,
     -95.5,
     0.204
    ],
    [
     -40.4,
     -95.5,
     0.234
    ],
    [
     -45.2,
     -95.5,
     0.192
    ],
    [
     -53.5,
     -91.4,
     0.009
    ],
    [
     -51.7,
     -85.9,
     0.009
    ],
    [
     -51.7,
     -82,
     0.01
    ],
    [
     -48.4,
     -81.2,
     0.01
    ],
    [
     -53.8,
     -88.4,
     0.009
    ],
    [
     -51.5,
     -92.1,
     0.009
    ],
    [
     -39.6,
     -95.5,
     0.291
    ],
    [
     -41.9,
     -95.5,
     0.181
    ],
    [
     -52.4,
     -94.1,
     0.013
    ],
    [
     -48.6,
     -87.3,
     0.01
    ],
    [
     -42.7,
     -85.3,
     0.01
    ],
    [
     -45.6,
     -87.3,
     0.01
    ],
    [
     -45.9,
     -88.3,
     0.01
    ]
   ]
  },
  {
   "t": 1784311312757,
   "pts": [
    [
     -51.4,
     -86.6,
     0.011
    ],
    [
     -50.6,
     -83,
     0.011
    ],
    [
     -50.6,
     -80.7,
     0.011
    ],
    [
     -55.5,
     -79.2,
     0.011
    ],
    [
     -53.1,
     -84.1,
     0.032
    ],
    [
     -52.1,
     -95.5,
     0.023
    ],
    [
     -51.8,
     -95.6,
     0.053
    ],
    [
     -52.1,
     -94.4,
     0.071
    ],
    [
     -46.6,
     -95.6,
     0.101
    ],
    [
     -54.3,
     -94.2,
     0.027
    ],
    [
     -53,
     -86.9,
     0.027
    ],
    [
     -53.2,
     -92,
     0.011
    ],
    [
     -48.6,
     -94.2,
     0.011
    ],
    [
     -60.2,
     -92.9,
     0.011
    ]
   ]
  },
  {
   "t": 1784311321710,
   "pts": [
    [
     -185.2,
     -54,
     0.226
    ],
    [
     -185.2,
     -59.8,
     0.357
    ],
    [
     -185.2,
     -76.1,
     0.29
    ],
    [
     -185.2,
     -76.6,
     0.206
    ],
    [
     -185.2,
     -68.2,
     0.204
    ],
    [
     -185.2,
     -56,
     0.256
    ],
    [
     -185.2,
     -46.8,
     0.245
    ],
    [
     -185.2,
     -46,
     0.22
    ],
    [
     -185.2,
     -55.3,
     0.248
    ],
    [
     -185.2,
     -76.9,
     0.178
    ],
    [
     -185.2,
     -75.5,
     0.173
    ],
    [
     -185.2,
     -67,
     0.209
    ],
    [
     -185.2,
     -51.2,
     0.229
    ],
    [
     -185.2,
     -45,
     0.223
    ],
    [
     -185.2,
     -50.1,
     0.2
    ],
    [
     -185.2,
     -67.3,
     0.178
    ],
    [
     -185.2,
     -75.5,
     0.098
    ],
    [
     -185.2,
     -59.9,
     0.242
    ],
    [
     -185.2,
     -51.7,
     0.26
    ],
    [
     -185.2,
     -53.6,
     0.165
    ],
    [
     -185.2,
     -68,
     0.132
    ],
    [
     -185.2,
     -67.4,
     0.163
    ],
    [
     -185.2,
     -58.4,
     0.199
    ]
   ]
  },
  {
   "t": 1784311330612,
   "pts": [
    [
     -165.9,
     -48.9,
     0.011
    ],
    [
     -170.2,
     -53.5,
     0.011
    ],
    [
     -166.8,
     -44.1,
     0.114
    ],
    [
     -176.2,
     -46.4,
     0.01
    ],
    [
     -175.8,
     -46.9,
     0.01
    ],
    [
     -169.5,
     -48.1,
     0.011
    ],
    [
     -170.5,
     -44.8,
     0.01
    ],
    [
     -169.1,
     -44.1,
     0.084
    ],
    [
     -168.6,
     -49.8,
     0.011
    ],
    [
     -169.4,
     -44.1,
     0.062
    ],
    [
     -170.8,
     -45.1,
     0.01
    ],
    [
     -169.3,
     -45.4,
     0.011
    ],
    [
     -163.1,
     -47.5,
     0.011
    ],
    [
     -157.2,
     -48.5,
     0.011
    ],
    [
     -157.2,
     -45.9,
     0.011
    ],
    [
     -156.1,
     -45.7,
     0.011
    ],
    [
     -157,
     -43.8,
     0.011
    ],
    [
     -156.8,
     -42.8,
     0.011
    ],
    [
     -157.6,
     -42.9,
     0.011
    ],
    [
     -159.8,
     -42.2,
     0.011
    ],
    [
     -160.1,
     -42.1,
     0.011
    ],
    [
     -159,
     -43.2,
     0.011
    ],
    [
     -159.4,
     -43.2,
     0.011
    ]
   ]
  },
  {
   "t": 1784311336894,
   "pts": [
    [
     -106.7,
     -40.7,
     0.012
    ],
    [
     -88.7,
     -40.9,
     0.096
    ],
    [
     -104.7,
     -39.6,
     0.012
    ],
    [
     -105.9,
     -41.8,
     0.012
    ],
    [
     -100,
     -39.8,
     0.011
    ],
    [
     -107.4,
     -40.3,
     0.012
    ],
    [
     -104.5,
     -41.3,
     0.012
    ],
    [
     -101.4,
     -43.3,
     0.012
    ]
   ]
  },
  {
   "t": 1784311340013,
   "pts": [
    [
     -78.8,
     -48.8,
     0.012
    ],
    [
     -78.8,
     -46.4,
     0.012
    ],
    [
     -68.1,
     -50.3,
     0.011
    ],
    [
     -70.9,
     -49.6,
     0.011
    ],
    [
     -77.9,
     -46.5,
     0.012
    ],
    [
     -61.2,
     -51.2,
     0.011
    ],
    [
     -73.3,
     -45,
     0.011
    ],
    [
     -64.2,
     -45.9,
     0.011
    ],
    [
     -60.9,
     -44.6,
     0.01
    ],
    [
     -68.5,
     -44.8,
     0.011
    ],
    [
     -64.9,
     -45.2,
     0.011
    ]
   ]
  }
 ],
 "audio": "note-2026-07-17T18-02-25-852Z.webm",
 "kind": "video",
 "coords": "plan inches; strokes [x,y,heightM]"
}